{"state":{"title":"Overlap Plan Improvement Tracker","updated":"2026-05-13T08:56:40.760Z","chapters":[{"subs":[],"name":"Chapter 1 - Introduction \u0026 Scope","id":"_chap1","open":true},{"subs":[],"name":"Chapter 2 - Methodology","id":"_chap2","open":true},{"subs":[],"name":"Chapter 3 - Analysis \u0026 Findings","id":"_chap3","open":true},{"subs":[],"name":"Chapter 4 - Discussion","id":"_chap4","open":true},{"subs":[],"name":"Chapter 5 - Conclusions \u0026 Recommendations","id":"_chap5","open":true}]},"activity":[]}